{
  "canvanboard": [
    {
      "title": 4,
      "content": 12,
      "id": 1,
      "deadLine": 22,
      "status": "todo",
      "manager": "백광천",
      "order": 1024
    },
    {
      "title": 4,
      "content": 12,
      "id": 2,
      "deadLine": 22,
      "status": "todo",
      "manager": "이광천",
      "order": 2048
    },
    {
      "title": 4,
      "content": 12,
      "id": 3,
      "deadLine": 22,
      "status": "todo",
      "manager": "삼광천",
      "order": 3072
    },
    {
      "title": 4,
      "content": 12,
      "id": 4,
      "deadLine": 22,
      "status": "done",
      "manager": "백광천",
      "order": 2816
    },
    {
      "title": 4,
      "content": 12,
      "id": 5,
      "deadLine": 22,
      "status": "done",
      "manager": "이광천",
      "order": 7168
    },
    {
      "title": 4,
      "content": 12,
      "id": 6,
      "deadLine": 22,
      "status": "doing",
      "manager": "삼광천",
      "order": 6240
    },
    {
      "title": 4,
      "content": 12,
      "id": 7,
      "deadLine": 22,
      "status": "doing",
      "manager": "백광천",
      "order": 5216
    },
    {
      "title": 4,
      "content": 12,
      "id": 8,
      "deadLine": 22,
      "status": "done",
      "manager": "이광천",
      "order": 5632
    },
    {
      "title": 4,
      "content": 12,
      "id": 9,
      "deadLine": 22,
      "status": "done",
      "manager": "삼광천",
      "order": 8704
    }
  ]
}